openhtf/__init__.py
openhtf/core/__init__.py
openhtf/core/measurements.py
openhtf/core/monitors.py
openhtf/core/phase_descriptor.py
openhtf/core/phase_executor.py
openhtf/core/phase_group.py
openhtf/core/test_descriptor.py
openhtf/core/test_executor.py
openhtf/core/test_record.py
openhtf/core/test_state.py
openhtf/examples/__init__.py
openhtf/examples/all_the_things.py
openhtf/examples/checkpoints.py
openhtf/examples/example_attachment.txt
openhtf/examples/example_plugs.py
openhtf/examples/frontend_example.py
openhtf/examples/hello_world.py
openhtf/examples/ignore_early_canceled_tests.py
openhtf/examples/measurements.py
openhtf/examples/phase_groups.py
openhtf/examples/repeat.py
openhtf/examples/stop_on_first_failure.py
openhtf/examples/with_plugs.py
openhtf/output/__init__.py
openhtf/output/callbacks/__init__.py
openhtf/output/callbacks/console_summary.py
openhtf/output/callbacks/json_factory.py
openhtf/output/callbacks/mfg_inspector.py
openhtf/output/proto/__init__.py
openhtf/output/proto/assembly_event_pb2.py
openhtf/output/proto/guzzle_pb2.py
openhtf/output/proto/mfg_event_converter.py
openhtf/output/proto/mfg_event_pb2.py
openhtf/output/proto/test_runs_converter.py
openhtf/output/proto/test_runs_pb2.py
openhtf/output/servers/__init__.py
openhtf/output/servers/dashboard_server.py
openhtf/output/servers/pub_sub.py
openhtf/output/servers/station_server.py
openhtf/output/servers/web_gui_server.py
openhtf/output/web_gui/COPYRIGHT
openhtf/output/web_gui/README.md
openhtf/output/web_gui/__init__.py
openhtf/output/web_gui/package-lock.json
openhtf/output/web_gui/package.json
openhtf/output/web_gui/tsconfig.json
openhtf/output/web_gui/tslint.json
openhtf/output/web_gui/typedoc.json
openhtf/output/web_gui/web_launcher.py
openhtf/output/web_gui/webpack.config.js
openhtf/output/web_gui/dist/index.html
openhtf/output/web_gui/dist/service-worker.js
openhtf/output/web_gui/dist/css/app.921dd742d96bd7480b68.css
openhtf/output/web_gui/dist/css/app.921dd742d96bd7480b68.css.map
spintop_openhtf-0.6.5.dist-info/AUTHORS
spintop_openhtf-0.6.5.dist-info/LICENSE
spintop_openhtf-0.6.5.dist-info/METADATA
spintop_openhtf-0.6.5.dist-info/WHEEL
spintop_openhtf-0.6.5.dist-info/top_level.txt
spintop_openhtf-0.6.5.dist-info/RECORD
