Metadata-Version: 2.1
Name: spintop-openhtf
Version: 0.6.5
Summary: An opinionated fork of OpenHTF by the team behind Spintop. OpenHTF is currently vendored-in.
Home-page: https://gitlab.com/tackv/spintop-openhtf
Author: William Laroche
Author-email: william.laroche@tackv.ca
Maintainer: William Laroche
Maintainer-email: william.laroche@tackv.ca
License: UNKNOWN
Platform: UNKNOWN
Provides-Extra: server
Provides-Extra: plugs.comport
Provides-Extra: plugs.ssh
Provides-Extra: plugs.visa
